<?xml version="1.0"?>
<ArrayOfQuestion xmlns:xsi="http://www.w3.org/2001/XMLSchema-instance" xmlns:xsd="http://www.w3.org/2001/XMLSchema">
  <Question>
    <text>Кошка - друг человека</text>
    <trueFalse>true</trueFalse>
  </Question>
  <Question>
    <text>В Японии ученики на доске пишут кисточкой с цветными чернилами</text>
    <trueFalse>true</trueFalse>
  </Question>
  <Question>
    <text>В Австралии практикуется применение одноразовых школьных досок</text>
    <trueFalse>false</trueFalse>
  </Question>
  <Question>
    <text>Авторучка была изобретена еще в Древнем Египте</text>
    <trueFalse>true</trueFalse>
  </Question>
  <Question>
    <text>Шариковая ручка сначала применялась только военными летчиками</text>
    <trueFalse>true</trueFalse>
  </Question>
  <Question>
    <text>В Африке выпускаются витаминизированные карандаши для детей, имеющих обыкновение грызть что попало</text>
    <trueFalse>true</trueFalse>
  </Question>
  <Question>
    <text>В некоторые виды цветных карандашей добавляется экстракт моркови для большей прочности грифеля</text>
    <trueFalse>false</trueFalse>
  </Question>
  <Question>
    <text>Римляне носили штаны</text>
    <trueFalse>false</trueFalse>
  </Question>
  <Question>
    <text>Если пчела ужалит кого-либо, то она погибнет</text>
    <trueFalse>true</trueFalse>
  </Question>
  <Question>
    <text>На зиму пингвины улетают на север</text>
    <trueFalse>false</trueFalse>
  </Question>
</ArrayOfQuestion>